pyamorph/__init__.py
pyamorph/__main__.py
pyamorph/display.py
pyamorph/dnest_functions.py
pyamorph/showresults.py
pyamorph_ccoverstreet-0.1.2.dist-info/LICENSE
pyamorph_ccoverstreet-0.1.2.dist-info/METADATA
pyamorph_ccoverstreet-0.1.2.dist-info/WHEEL
pyamorph_ccoverstreet-0.1.2.dist-info/top_level.txt
pyamorph_ccoverstreet-0.1.2.dist-info/RECORD
